{
  "$schema": "https://shadcn-vue.com/schema/registry-item.json",
  "name": "signup-03",
  "type": "registry:block",
  "description": "A signup page with a muted background color.",
  "registryDependencies": [
    "button",
    "card",
    "field",
    "input"
  ],
  "files": [
    {
      "path": "registry/new-york-v4/blocks/signup-03/page.vue",
      "content": "<script setup lang=\"ts\">\r\nimport { GalleryVerticalEnd } from \"lucide-vue-next\"\r\n\r\nimport SignupForm from \"@/registry/new-york-v4/blocks/signup-03/components/SignupForm.vue\"\r\n</script>\r\n\r\n<template>\r\n  <div class=\"bg-muted flex min-h-svh flex-col items-center justify-center gap-6 p-6 md:p-10\">\r\n    <div class=\"flex w-full max-w-sm flex-col gap-6\">\r\n      <a href=\"#\" class=\"flex items-center gap-2 self-center font-medium\">\r\n        <div class=\"bg-primary text-primary-foreground flex size-6 items-center justify-center rounded-md\">\r\n          <GalleryVerticalEnd class=\"size-4\" />\r\n        </div>\r\n        Acme Inc.\r\n      </a>\r\n      <SignupForm />\r\n    </div>\r\n  </div>\r\n</template>\r\n",
      "type": "registry:page",
      "target": "pages/signup/index.vue"
    },
    {
      "path": "registry/new-york-v4/blocks/signup-03/components/SignupForm.vue",
      "content": "<script setup lang=\"ts\">\r\nimport type { HTMLAttributes } from \"vue\"\r\nimport { cn } from \"@/registry/new-york-v4/lib/utils\"\r\nimport { Button } from \"@/registry/new-york-v4/ui/button\"\r\nimport {\r\n  Card,\r\n  CardContent,\r\n  CardDescription,\r\n  CardHeader,\r\n  CardTitle,\r\n} from \"@/registry/new-york-v4/ui/card\"\r\nimport {\r\n  Field,\r\n  FieldDescription,\r\n  FieldGroup,\r\n  FieldLabel,\r\n} from \"@/registry/new-york-v4/ui/field\"\r\nimport { Input } from \"@/registry/new-york-v4/ui/input\"\r\n\r\nconst props = defineProps<{\r\n  class?: HTMLAttributes[\"class\"]\r\n}>()\r\n</script>\r\n\r\n<template>\r\n  <div :class=\"cn('flex flex-col gap-6', props.class)\">\r\n    <Card>\r\n      <CardHeader class=\"text-center\">\r\n        <CardTitle class=\"text-xl\">\r\n          Create your account\r\n        </CardTitle>\r\n        <CardDescription>\r\n          Enter your email below to create your account\r\n        </CardDescription>\r\n      </CardHeader>\r\n      <CardContent>\r\n        <form>\r\n          <FieldGroup>\r\n            <Field>\r\n              <FieldLabel for=\"name\">\r\n                Full Name\r\n              </FieldLabel>\r\n              <Input id=\"name\" type=\"text\" placeholder=\"John Doe\" required />\r\n            </Field>\r\n            <Field>\r\n              <FieldLabel for=\"email\">\r\n                Email\r\n              </FieldLabel>\r\n              <Input\r\n                id=\"email\"\r\n                type=\"email\"\r\n                placeholder=\"m@example.com\"\r\n                required\r\n              />\r\n            </Field>\r\n            <Field>\r\n              <Field class=\"grid grid-cols-2 gap-4\">\r\n                <Field>\r\n                  <FieldLabel for=\"password\">\r\n                    Password\r\n                  </FieldLabel>\r\n                  <Input id=\"password\" type=\"password\" required />\r\n                </Field>\r\n                <Field>\r\n                  <FieldLabel for=\"confirm-password\">\r\n                    Confirm Password\r\n                  </FieldLabel>\r\n                  <Input id=\"confirm-password\" type=\"password\" required />\r\n                </Field>\r\n              </Field>\r\n              <FieldDescription>\r\n                Must be at least 8 characters long.\r\n              </FieldDescription>\r\n            </Field>\r\n            <Field>\r\n              <Button type=\"submit\">\r\n                Create Account\r\n              </Button>\r\n              <FieldDescription class=\"text-center\">\r\n                Already have an account? <a href=\"#\">Sign in</a>\r\n              </FieldDescription>\r\n            </Field>\r\n          </FieldGroup>\r\n        </form>\r\n      </CardContent>\r\n    </Card>\r\n    <FieldDescription class=\"px-6 text-center\">\r\n      By clicking continue, you agree to our <a href=\"#\">Terms of Service</a>\r\n      and <a href=\"#\">Privacy Policy</a>.\r\n    </FieldDescription>\r\n  </div>\r\n</template>\r\n",
      "type": "registry:component"
    }
  ],
  "categories": [
    "authentication",
    "signup"
  ]
}
